CHANGES.txt
bootstrap.py
buildout.cfg
setup.py
thoughts.txt
scripts/performance.py
src/traject/__init__.py
src/traject/_traject.py
src/traject/tests.py
src/traject/traject.txt
src/traject.egg-info/PKG-INFO
src/traject.egg-info/SOURCES.txt
src/traject.egg-info/dependency_links.txt
src/traject.egg-info/entry_points.txt
src/traject.egg-info/not-zip-safe
src/traject.egg-info/requires.txt
src/traject.egg-info/top_level.txt