Metadata-Version: 1.0
Name: traject
Version: 0.10.1
Summary: A URL dispatch to object system that combines aspects of routing and traversal.
Home-page: UNKNOWN
Author: Martijn Faassen
Author-email: faassen@startifact.com
License: ZPL
Keywords: route routing url traverse traversing web
Platform: UNKNOWN
Classifier: Development Status :: 4 - Beta
Classifier: Environment :: Web Environment
Classifier: Intended Audience :: Developers
Classifier: License :: OSI Approved :: Zope Public License
Classifier: Operating System :: OS Independent
Classifier: Programming Language :: Python
Classifier: Topic :: Internet :: WWW/HTTP
Classifier: Topic :: Software Development :: Libraries
